pystorclitui/__init__.py
pystorclitui/app.py
pystorclitui/header.py
pystorclitui/storcliTree.py
pystorclitui/storclicmdtui.py
pystorclitui/version.py
pystorclitui/bin/storcliTUI.py
pystorclitui/views/__init__.py
pystorclitui/views/drive.py
pystorclitui/widgets/__init__.py
pystorclitui/widgets/buttonBox.py
pystorclitui/widgets/messageBox.py
PyStorCLITUI-0.0.1.dev9.dist-info/LICENSE
PyStorCLITUI-0.0.1.dev9.dist-info/METADATA
PyStorCLITUI-0.0.1.dev9.dist-info/WHEEL
PyStorCLITUI-0.0.1.dev9.dist-info/entry_points.txt
PyStorCLITUI-0.0.1.dev9.dist-info/top_level.txt
PyStorCLITUI-0.0.1.dev9.dist-info/RECORD
