Metadata-Version: 2.1
Name: PyStorCLITUI
Version: 0.0.1.dev9
Summary: Python StorCLI TUI
Author-email: Rafael Leira <rafael.leira@naudit.es>
License: BSD-3-Clause
Project-URL: Homepage, https://github.com/Naudit/pystorcliTUI
Keywords: storcli,wrapper,cli,tui,textual
Classifier: Programming Language :: Python :: 3
Classifier: Intended Audience :: Developers
Classifier: Intended Audience :: Information Technology
Classifier: Intended Audience :: System Administrators
Classifier: License :: OSI Approved :: BSD License
Classifier: Natural Language :: English
Classifier: Operating System :: POSIX
Classifier: Topic :: System :: Hardware :: Hardware Drivers
Classifier: Topic :: System :: Installation/Setup
Classifier: Topic :: Software Development :: Libraries :: Python Modules
Classifier: Programming Language :: Python
Classifier: Development Status :: 3 - Alpha
Requires-Python: >=3.8
License-File: LICENSE
Requires-Dist: pyStorCLI2 (>=0.6.2)
Requires-Dist: textual (>=0.19.1)
Provides-Extra: dev
Requires-Dist: pytest ; extra == 'dev'
Requires-Dist: pytest-cov ; extra == 'dev'
Requires-Dist: coveralls ; extra == 'dev'
Requires-Dist: pdoc ; extra == 'dev'
Requires-Dist: mypy ; extra == 'dev'
